pdf2seg/__init__.py
pdf2seg/__main__.py
pdf2seg-1.0.2.dist-info/licenses/LICENSE
pdf2seg-1.0.2.dist-info/METADATA
pdf2seg-1.0.2.dist-info/WHEEL
pdf2seg-1.0.2.dist-info/entry_points.txt
pdf2seg-1.0.2.dist-info/top_level.txt
pdf2seg-1.0.2.dist-info/RECORD
