Metadata-Version: 2.4
Name: pdf2seg
Version: 1.0.2
Summary: Tokenization-free PDF segmentation using OCR and spaCy span-aware chunking
Author-email: Kara Rawson <rawsonkara@gmail.com>
License: MIT
Project-URL: Homepage, https://github.com/p3nGu1nZz/pdf2seg
Project-URL: Repository, https://github.com/p3nGu1nZz/pdf2seg
Project-URL: Issues, https://github.com/p3nGu1nZz/pdf2seg/issues
Keywords: PDF,OCR,tokenization-free,text segmentation,NLP,easyocr,spacy,preprocessing,language models,pointer network
Classifier: Development Status :: 5 - Production/Stable
Classifier: Intended Audience :: Developers
Classifier: License :: OSI Approved :: MIT License
Classifier: Programming Language :: Python :: 3.11
Classifier: Programming Language :: Python :: 3.12
Classifier: Programming Language :: Python :: 3.13
Classifier: Topic :: Text Processing :: Linguistic
Classifier: Topic :: Scientific/Engineering :: Artificial Intelligence
Requires-Python: >=3.11
License-File: LICENSE
Requires-Dist: easyocr>=1.7.2
Requires-Dist: numpy>=2.3.1
Requires-Dist: pdf2image>=1.17.0
Requires-Dist: pillow>=11.2.1
Requires-Dist: pip>=25.1.1
Requires-Dist: rich>=14.0.0
Requires-Dist: spacy>=3.8.7
Requires-Dist: torch>=2.7.1
Requires-Dist: torchvision>=0.22.1
Dynamic: license-file
